<?xml version="1.0" encoding="UTF-8"?>
<alpino_ds version="1.3">
  <node begin="0" cat="top" end="7" id="0" rel="top">
    <node begin="0" cat="smain" end="7" id="1" rel="--">
      <node begin="0" case="nom" def="def" end="1" gen="de" genus="masc" getal="ev" id="2" index="1" lemma="hij" naamval="nomin" num="sg" pdtype="pron" per="thi" persoon="3" pos="pron" postag="VNW(pers,pron,nomin,vol,3,ev,masc)" pt="vnw" rel="su" rnum="sg" root="hij" status="vol" vwtype="pers" wh="nwh" word="Hij"/>
      <node begin="1" end="2" id="3" infl="sg_heeft" lemma="hebben" pos="verb" postag="WW(pv,tgw,met-t)" pt="ww" pvagr="met-t" pvtijd="tgw" rel="hd" root="heb" sc="aux_psp_hebben" stype="declarative" tense="present" v_per="thi" word="heeft" wvorm="pv"/>
      <node begin="0" cat="ppart" end="7" id="4" rel="vc">
        <node begin="0" end="1" id="5" index="1" rel="su"/>
        <node begin="2" end="3" genus="onz" getal="ev" id="6" infl="het" lemma="het" naamval="stan" pdtype="pron" persoon="3" pos="det" postag="VNW(pers,pron,stan,red,3,ev,onz)" pt="vnw" rel="obj1" rnum="sg" root="het" status="red" vwtype="pers" wh="nwh" word="het"/>
        <node begin="3" cat="np" end="5" id="7" rel="mod">
          <node begin="3" end="4" id="8" lemma="circa" pos="adv" postag="BW()" pt="bw" rel="mod" root="circa" sc="noun_prep" word="circa"/>
          <node begin="4" end="5" id="9" lemma="1970" neclass="year" numtype="hoofd" pos="noun" positie="vrij" postag="TW(hoofd,vrij)" pt="tw" rel="hd" root="1970" word="1970"/>
        </node>
        <node begin="5" end="6" id="10" lemma="al" pos="adv" postag="BW()" pt="bw" rel="mod" root="al" word="al"/>
        <node begin="6" buiging="zonder" end="7" id="11" infl="psp" lemma="roepen" pos="verb" positie="vrij" postag="WW(vd,vrij,zonder)" pt="ww" rel="hd" root="roep" sc="transitive" word="geroepen" wvorm="vd"/>
      </node>
    </node>
  </node>
  <sentence>Hij heeft het circa 1970 al geroepen</sentence>
</alpino_ds>
