<?xml version="1.0" encoding="UTF-8"?>
<alpino_ds version="1.3">
  <node begin="0" cat="top" end="27" id="0" rel="top">
    <node begin="19" end="20" id="1" lemma="," pos="punct" postag="LET()" pt="let" rel="--" root="," word=","/>
    <node begin="0" cat="smain" end="26" id="2" rel="--">
      <node begin="0" cat="np" end="6" id="3" index="1" rel="su">
        <node begin="0" end="1" id="4" lemma="de" lwtype="bep" naamval="stan" npagr="rest" pos="det" postag="LID(bep,stan,rest)" pt="lid" rel="det" root="de" word="De"/>
        <node begin="1" end="2" genus="zijd" getal="ev" graad="basis" id="5" lemma="man" naamval="stan" ntype="soort" pos="noun" postag="N(soort,ev,basis,zijd,stan)" pt="n" rel="hd" root="man" word="man"/>
        <node begin="2" cat="pp" end="6" id="6" rel="mod">
          <node begin="2" end="3" id="7" lemma="uit" pos="prep" postag="VZ(init)" pt="vz" rel="hd" root="uit" vztype="init" word="uit"/>
          <node begin="3" cat="mwu" end="6" id="8" rel="obj1">
            <node begin="3" end="4" id="9" lemma="Nederhorst" pos="noun" postag="SPEC(deeleigen)" pt="spec" rel="mwp" root="Nederhorst" spectype="deeleigen" word="Nederhorst"/>
            <node begin="4" end="5" id="10" lemma="den" pos="noun" postag="SPEC(deeleigen)" pt="spec" rel="mwp" root="den" spectype="deeleigen" word="den"/>
            <node begin="5" end="6" id="11" lemma="Berg" pos="noun" postag="SPEC(deeleigen)" pt="spec" rel="mwp" root="Berg" spectype="deeleigen" word="Berg"/>
          </node>
        </node>
      </node>
      <node begin="6" end="7" id="12" lemma="moeten" pos="verb" postag="WW(pv,verl,ev)" pt="ww" pvagr="ev" pvtijd="verl" rel="hd" root="moet" word="moest" wvorm="pv"/>
      <node begin="0" cat="inf" end="26" id="13" rel="vc">
        <node begin="0" end="6" id="14" index="1" rel="su"/>
        <node begin="7" cat="pp" end="11" id="15" rel="mod">
          <node begin="7" end="8" id="16" lemma="met" pos="prep" postag="VZ(init)" pt="vz" rel="hd" root="met" vztype="init" word="met"/>
          <node begin="8" cat="np" end="11" id="17" rel="obj1">
            <node begin="8" buiging="zonder" end="9" getal="ev" id="18" lemma="zijn" naamval="stan" npagr="agr" pdtype="det" persoon="3" pos="det" positie="prenom" postag="VNW(bez,det,stan,vol,3,ev,prenom,zonder,agr)" pt="vnw" rel="det" root="zijn" status="vol" vwtype="bez" word="zijn"/>
            <node begin="9" buiging="zonder" end="10" graad="basis" id="19" lemma="eigen_bouw" pos="noun" positie="vrij" postag="ADJ(vrij,basis,zonder)" pt="adj" rel="hd" root="bouw" word="eigenbouw"/>
            <node begin="10" end="11" genus="onz" getal="ev" graad="basis" id="20" lemma="Jamathi" naamval="stan" ntype="eigen" pos="noun" postag="N(eigen,ev,basis,onz,stan)" pt="n" rel="app" root="Jamathi" word="Jamathi"/>
          </node>
        </node>
        <node begin="13" buiging="zonder" end="14" id="21" lemma="leveren" pos="verb" positie="vrij" postag="WW(inf,vrij,zonder)" pt="ww" rel="hd" root="lever" word="leveren" wvorm="inf"/>
        <node begin="11" cat="np" end="26" id="22" rel="obj1">
          <node begin="11" buiging="met-e" end="12" graad="basis" id="23" lemma="fel" naamval="stan" pos="adj" positie="prenom" postag="ADJ(prenom,basis,met-e,stan)" pt="adj" rel="mod" root="fel" word="felle"/>
          <node begin="12" end="13" genus="zijd" getal="ev" graad="basis" id="24" lemma="strijd" naamval="stan" ntype="soort" pos="noun" postag="N(soort,ev,basis,zijd,stan)" pt="n" rel="hd" root="strijd" word="strijd"/>
          <node begin="14" cat="pp" end="26" id="25" rel="mod">
            <node begin="14" end="15" id="26" lemma="met" pos="prep" postag="VZ(init)" pt="vz" rel="hd" root="met" vztype="init" word="met"/>
            <node begin="15" cat="np" end="26" id="27" rel="obj1">
              <node begin="15" end="16" id="28" lemma="de" lwtype="bep" naamval="stan" npagr="rest" pos="det" postag="LID(bep,stan,rest)" pt="lid" rel="det" root="de" word="de"/>
              <node begin="16" end="17" genus="zijd" getal="ev" graad="basis" id="29" lemma="Brit" naamval="stan" ntype="eigen" pos="noun" postag="N(eigen,ev,basis,zijd,stan)" pt="n" rel="hd" root="Brit" word="Brit"/>
              <node begin="17" cat="mwu" end="19" id="30" rel="app">
                <node begin="17" end="18" id="31" lemma="Barry" pos="noun" postag="SPEC(deeleigen)" pt="spec" rel="mwp" root="Barry" spectype="deeleigen" word="Barry"/>
                <node begin="18" end="19" id="32" lemma="Smith" pos="noun" postag="SPEC(deeleigen)" pt="spec" rel="mwp" root="Smith" spectype="deeleigen" word="Smith"/>
              </node>
              <node begin="20" cat="np" end="26" id="33" rel="app">
                <node begin="20" end="21" genus="zijd" getal="ev" graad="basis" id="34" lemma="triomfator" naamval="stan" ntype="soort" pos="noun" postag="N(soort,ev,basis,zijd,stan)" pt="n" rel="hd" root="triomfator" word="triomfator"/>
                <node begin="21" cat="pp" end="26" id="35" rel="mod">
                  <node begin="21" end="22" id="36" lemma="bij" pos="prep" postag="VZ(init)" pt="vz" rel="hd" root="bij" vztype="init" word="bij"/>
                  <node begin="22" cat="np" end="26" id="37" rel="obj1">
                    <node begin="22" end="23" id="38" lemma="de" lwtype="bep" naamval="stan" npagr="rest" pos="det" postag="LID(bep,stan,rest)" pt="lid" rel="det" root="de" word="de"/>
                    <node begin="23" end="24" getal="mv" graad="basis" id="39" lemma="TT_race" ntype="soort" pos="noun" postag="N(soort,mv,basis)" pt="n" rel="hd" root="race" word="TT-races"/>
                    <node begin="24" cat="pp" end="26" id="40" rel="mod">
                      <node begin="24" end="25" id="41" lemma="in" pos="prep" postag="VZ(init)" pt="vz" rel="hd" root="in" vztype="init" word="in"/>
                      <node begin="25" end="26" genus="onz" getal="ev" graad="basis" id="42" lemma="Assen" naamval="stan" ntype="eigen" pos="noun" postag="N(eigen,ev,basis,onz,stan)" pt="n" rel="obj1" root="Assen" word="Assen"/>
                    </node>
                  </node>
                </node>
              </node>
            </node>
          </node>
        </node>
      </node>
    </node>
    <node begin="26" end="27" id="43" lemma="." pos="punct" postag="LET()" pt="let" rel="--" root="." word="."/>
  </node>
  <sentence>De man uit Nederhorst den Berg moest met zijn eigenbouw Jamathi felle strijd leveren met de Brit Barry Smith , triomfator bij de TT-races in Assen .</sentence>
</alpino_ds>
